{
    "_config_name": "hybridauth.settings",
    "hybridauth_required_fields": {
        "email": "email",
        "firstName": 0,
        "lastName": 0,
        "gender": 0
    },
    "hybridauth_widget_title": "",
    "hybridauth_widget_type": "list",
    "hybridauth_widget_use_overlay": 0,
    "hybridauth_widget_link_text": "",
    "hybridauth_widget_link_title": "",
    "hybridauth_widget_icon_pack": "hybridauth_48",
    "hybridauth_widget_weight": "",
    "hybridauth_widget_hide_links": 0,
    "hybridauth_register": "0",
    "hybridauth_email_verification": "0",
    "hybridauth_email_verification_subject": "Account details for [user:name] at [site:name]",
    "hybridauth_email_verification_body": "[user:name],\r\n\r\nThank you for registering at [site:name]. You need to confirm your e-mail address by clicking this link or copying and pasting it to your browser:\r\n\r\n[user:one-time-login-url]\r\n\r\nThis link can only be used once to log in and activate your account.\r\n\r\nAfter that, you will be able to log in at [site:login-url] using your [user:hybridauth:provider] account.\r\n\r\n--  [site:name] team",
    "hybridauth_pictures": 0,
    "hybridauth_username": "[user:hybridauth:email]",
    "hybridauth_display_name": "",
    "hybridauth_registration_username_change": 0,
    "hybridauth_registration_password": 0,
    "hybridauth_override_realname": 0,
    "hybridauth_disable_username_change": 1,
    "hybridauth_remove_password_fields": 0,
    "hybridauth_forms": {
        "user_login": "user_login",
        "user_login_block": "user_login_block",
        "comment_form": "comment_form",
        "user_register_form": 0
    },
    "hybridauth_destination": "",
    "hybridauth_destination_error": "",
    "hybridauth_duplicate_emails": "1",
    "hybridauth_proxy": "",
    "hybridauth_debug": false,
    "vtabs__active_tab": "",
    "hybridauth_providers": {
        "AOL": 0,
        "Facebook": 0,
        "Foursquare": 0,
        "Google": 0,
        "LinkedIn": 0,
        "Live": 0,
        "MySpace": 0,
        "OpenID": 0,
        "Twitter": 0,
        "Yahoo": 0,
        "px500": 0,
        "Disqus": 0,
        "FamilySearch": 0,
        "Geni": 0,
        "GitHub": 0,
        "Goodreads": 0,
        "HumanitarianId": 0,
        "Identica": 0,
        "Instagram": 0,
        "LastFM": 0,
        "Mailru": 0,
        "Murmur": 0,
        "MyHeritage": 0,
        "Odnoklassniki": 0,
        "Pixnet": 0,
        "Plurk": 0,
        "QQ": 0,
        "Sina": 0,
        "Skyrock": 0,
        "Steam": 0,
        "Tumblr": 0,
        "TwitchTV": 0,
        "Viadeo": 0,
        "Vimeo": 0,
        "Vkontakte": 0,
        "Yandex": 0
    }
}
